dd_tool/__init__.py
dd_tool/downloader.py
dd_tool-0.0.3.dist-info/METADATA
dd_tool-0.0.3.dist-info/WHEEL
dd_tool-0.0.3.dist-info/entry_points.txt
dd_tool-0.0.3.dist-info/top_level.txt
dd_tool-0.0.3.dist-info/RECORD
