Metadata-Version: 2.1
Name: dd-tool
Version: 0.0.3
Summary: Download images from Google search
Home-page: https://github.com/piggaga/dd-tool
Author: 豬嘎嘎
Author-email: piggaga.company@gmail.com
Classifier: Programming Language :: Python :: 3
Classifier: License :: OSI Approved :: MIT License
Classifier: Operating System :: OS Independent
Requires-Python: >=3.6
Requires-Dist: requests
Requires-Dist: tqdm
Requires-Dist: rich
